[
    {
        "name": "Stores",
        "id": "stores",
        "class_list": " menu_btn_label",
        "href": "/stores"
    },
    {
        "name": "Promotions",
        "id": "promotions",
        "class_list": " menu_btn_label",
        "href": "/promotions"
    },
    {
        "name": "Events",
        "id": "events",
        "class_list": " menu_btn_label",
        "href": "/events"
    },
    {
        "name": "Jobs",
        "id": "jobs",
        "class_list": " menu_btn_label",
        "href": "/jobs"
    },
    {
        "name": "Contact Us",
        "id": "contact_us",
        "class_list": " menu_btn_label",
        "href": "/contact_us"
    }
]